prntscraper/Exceptions.py
prntscraper/__init__.py
prntscraper/scraper.py
prntscraper/upload.py
prntscraper-2.6.dist-info/LICENSE
prntscraper-2.6.dist-info/METADATA
prntscraper-2.6.dist-info/WHEEL
prntscraper-2.6.dist-info/top_level.txt
prntscraper-2.6.dist-info/RECORD
