Metadata-Version: 2.1
Name: prntscraper
Version: 2.6
Summary: Pulls random images from https://prnt.sc
Home-page: https://github.com/ItzBlinkzy/prnt.sc-scraper
Author: Itz Blinkzy
Author-email: legendarystone12@gmail.com
License: GNU
Keywords: scraper prnt.sc prntscraper fuskering
Classifier: Programming Language :: Python :: 3
Classifier: License :: OSI Approved :: GNU General Public License v3 or later (GPLv3+)
Classifier: Operating System :: OS Independent
Requires-Python: >=3.7
License-File: LICENSE
Requires-Dist: requests
Requires-Dist: bs4
Requires-Dist: tqdm
Requires-Dist: selenium
